redis_models/__init__.py
redis_models/errors.py
redis_models/models.py
redis_models-0.4.3.dist-info/LICENSE
redis_models-0.4.3.dist-info/WHEEL
redis_models-0.4.3.dist-info/METADATA
redis_models-0.4.3.dist-info/RECORD
