Metadata-Version: 2.1
Name: redis_models
Version: 0.4.3
Summary: This package provides a simple model structure for redis based storage.
Author-email: nejdetckenobi <nejdetyucesoy@gmail.com>
Classifier: License :: OSI Approved :: MIT License
Project-URL: Home, https://github.com/nejdetckenobi/redis_models
